pyplwnxml/__init__.py
pyplwnxml/__version__.py
pyplwnxml/enums.py
pyplwnxml/parser.py
pyplwnxml/utils.py
pyplwnxml/wordnet.py
pyplwnxml/tests/__init__.py
pyplwnxml/tests/test_plwnxmlParser.py
pyplwnxml-1.1.dist-info/DESCRIPTION.rst
pyplwnxml-1.1.dist-info/METADATA
pyplwnxml-1.1.dist-info/RECORD
pyplwnxml-1.1.dist-info/WHEEL
pyplwnxml-1.1.dist-info/metadata.json
pyplwnxml-1.1.dist-info/top_level.txt
