Metadata-Version: 2.0
Name: pyplwnxml
Version: 1.1
Summary: Parser for plwnxml (format of polish wordnet - słowosieć)
Home-page: https://github.com/red-rocket-dev/pyplwnxml
Author: Jakub Płonka
Author-email: redrocketdev@gmail.com
License: ISC
Requires-Dist: aenum
